euphony/__init__.py
euphony/player.py
euphony/music_templates/bach_preclude_c.mp3
euphony/music_templates/beethoven_fur_elise.mp3
euphony/music_templates/mozart_sonata_small.mp3
euphony-0.0.9.dist-info/LICENSE
euphony-0.0.9.dist-info/METADATA
euphony-0.0.9.dist-info/WHEEL
euphony-0.0.9.dist-info/top_level.txt
euphony-0.0.9.dist-info/RECORD
