Metadata-Version: 2.1
Name: euphony
Version: 0.0.9
Summary: Play music while your code runs
Home-page: https://github.com/vinaykale64/euphony
Author: Vinay Dinkar Kale
Author-email: vinaykale64@protonmail.com
License: MIT
Platform: UNKNOWN
Classifier: License :: OSI Approved :: MIT License
Classifier: Programming Language :: Python
Classifier: Programming Language :: Python :: 2
Classifier: Programming Language :: Python :: 3
Requires-Dist: pygame (>=2.0.0)
